ziplip/__init__.py
ziplip/cli.py
ziplip/ziplip.sh
ziplip-2.1.2.dist-info/LICENSE
ziplip-2.1.2.dist-info/METADATA
ziplip-2.1.2.dist-info/WHEEL
ziplip-2.1.2.dist-info/entry_points.txt
ziplip-2.1.2.dist-info/top_level.txt
ziplip-2.1.2.dist-info/RECORD
