Metadata-Version: 2.1
Name: ziplip
Version: 2.1.2
Summary: ziplip - Zip File Password Brute Force Tool
Home-page: https://mrfidal.in/cyber-security/ziplip
Author: Fidal
Author-email: mrfidal@proton.me
License: MIT
Keywords: zip file,brute force,enumeration,scanning,mrfidal,cyber security
Classifier: Development Status :: 5 - Production/Stable
Classifier: Intended Audience :: Information Technology
Classifier: Intended Audience :: System Administrators
Classifier: License :: OSI Approved :: MIT License
Classifier: Programming Language :: Python :: 3
Classifier: Programming Language :: Python :: 3.11
Classifier: Topic :: Security
License-File: LICENSE
Requires-Dist: requests
